mrs_tools/__init__.py
mrs_tools/constants.py
nifti_mrs/__init__.py
nifti_mrs/_version.py
nifti_mrs/create_nmrs.py
nifti_mrs/definitions.py
nifti_mrs/hdr_ext.py
nifti_mrs/nifti_mrs.py
nifti_mrs/utils.py
nifti_mrs/validator.py
nifti_mrs/vis.py
nifti_mrs/standard/definitions.json
nifti_mrs/tools/__init__.py
nifti_mrs/tools/misc.py
nifti_mrs/tools/reorder.py
nifti_mrs/tools/reshape.py
nifti_mrs/tools/split_merge.py
nifti_mrs-1.3.4.dist-info/licenses/LICENSE
nifti_mrs-1.3.4.dist-info/METADATA
nifti_mrs-1.3.4.dist-info/WHEEL
nifti_mrs-1.3.4.dist-info/entry_points.txt
nifti_mrs-1.3.4.dist-info/top_level.txt
nifti_mrs-1.3.4.dist-info/RECORD
