Metadata-Version: 2.4
Name: nifti_mrs
Version: 1.3.4
Summary: Software tools for the NIfTI-MRS data format
Home-page: https://github.com/wtclarke/nifti_mrs_tools
Author: William Clarke
Author-email: william.clarke@ndcn.ox.ac.uk
License: BSD 3-Clause License
Keywords: MRS
Classifier: Programming Language :: Python :: 3
Classifier: Programming Language :: Python :: 3.10
Classifier: Programming Language :: Python :: 3.11
Classifier: Programming Language :: Python :: 3.12
Classifier: Programming Language :: Python :: 3.13
Classifier: Programming Language :: Python :: 3.14
Requires-Python: >=3.10
License-File: LICENSE
Requires-Dist: numpy
Requires-Dist: nibabel>=5.3
Requires-Dist: fslpy
Requires-Dist: importlib_resources; python_version < "3.10"
Provides-Extra: vis
Requires-Dist: fsl-mrs; extra == "vis"
Dynamic: license-file
